stalk/__init__.py
stalk/io/FilesFunction.py
stalk/io/FilesLoader.py
stalk/io/GeometryLoader.py
stalk/io/GeometryWriter.py
stalk/io/PesLoader.py
stalk/io/XyzGeometry.py
stalk/io/__init__.py
stalk/ls/ErrorSurface.py
stalk/ls/FittingFunction.py
stalk/ls/FittingResult.py
stalk/ls/LineSearch.py
stalk/ls/LineSearchBase.py
stalk/ls/LineSearchGrid.py
stalk/ls/LsSettings.py
stalk/ls/TargetLineSearch.py
stalk/ls/TargetLineSearchBase.py
stalk/ls/TlsSettings.py
stalk/ls/__init__.py
stalk/lsi/LineSearchIteration.py
stalk/lsi/__init__.py
stalk/lsi/util.py
stalk/nexus/NexusGeometry.py
stalk/nexus/NexusPes.py
stalk/nexus/NexusStructure.py
stalk/nexus/PwscfGeometry.py
stalk/nexus/PwscfPes.py
stalk/nexus/QmcPes.py
stalk/nexus/__init__.py
stalk/params/GeometryResult.py
stalk/params/LineSearchPoint.py
stalk/params/Parameter.py
stalk/params/ParameterHessian.py
stalk/params/ParameterSet.py
stalk/params/ParameterStructure.py
stalk/params/PesFunction.py
stalk/params/PesResult.py
stalk/params/__init__.py
stalk/params/util.py
stalk/pls/ParallelLineSearch.py
stalk/pls/TargetParallelLineSearch.py
stalk/pls/__init__.py
stalk/util/EffectiveVariance.py
stalk/util/FunctionCaller.py
stalk/util/__init__.py
stalk/util/util.py
stalk_qmc-0.2.1.dist-info/METADATA
stalk_qmc-0.2.1.dist-info/WHEEL
stalk_qmc-0.2.1.dist-info/licenses/LICENSE
stalk_qmc-0.2.1.dist-info/RECORD
