Metadata-Version: 2.4
Name: stalk-qmc
Version: 0.2.1
License-File: LICENSE
Requires-Dist: dill>=0.3.9
Requires-Dist: matplotlib>=3.9.2
Requires-Dist: numpy>=2.0.1
Requires-Dist: scipy>=1.14.1
